aqa32/__init__.py
aqa32/__main__.py
aqa32/assembler.py
aqa32/constants.py
aqa32/emulator.py
aqa32/instructions.py
aqa32/render.py
aqa32-4.5.dist-info/METADATA
aqa32-4.5.dist-info/WHEEL
aqa32-4.5.dist-info/top_level.txt
aqa32-4.5.dist-info/zip-safe
aqa32-4.5.dist-info/RECORD
