Metadata-Version: 2.1
Name: aqa32
Version: 4.5
Summary: AQA32 Instruction Set: Assembler and Emulator
Home-page: https://github.com/speyermr/aqa32
Author: E G Speyer
Author-email: python@edwardspeyer.com
License: MIT
Platform: UNKNOWN
